<?xml version="1.0" encoding="utf-8" ?><dwsync><file name=".DS_Store" server="sonyainc.net/public_html/" local="3480890595" remote="12076176152" /><file name="app.js" server="sonyainc.net/public_html/" local="3486241221" remote="12076176152" /><file name="comment-reply.min.js" server="sonyainc.net/public_html/" local="3480890595" remote="12076176152" /><file name="custom.modernizr.js" server="sonyainc.net/public_html/" local="3480890595" remote="12076176152" /><file name="foundation.min.js" server="sonyainc.net/public_html/" local="3480890595" remote="12076176152" /><file name="justgage.1.0.1.min.js" server="sonyainc.net/public_html/" local="3480890595" remote="12076176152" /><file name="raphael.2.1.0.min.js" server="sonyainc.net/public_html/" local="3480890595" remote="12076176152" /><file name="waypoints.min.js" server="sonyainc.net/public_html/" local="3480890595" remote="12076176152" /><file name="wpgroho.js" server="sonyainc.net/public_html/" local="3480890595" remote="12076176152" /></dwsync>